mmv_hitl4trk/__init__.py
mmv_hitl4trk/_analysis.py
mmv_hitl4trk/_evaluation.py
mmv_hitl4trk/_grabber.py
mmv_hitl4trk/_logger.py
mmv_hitl4trk/_processing.py
mmv_hitl4trk/_reader.py
mmv_hitl4trk/_segmentation.py
mmv_hitl4trk/_selector.py
mmv_hitl4trk/_tracking.py
mmv_hitl4trk/_widget.py
mmv_hitl4trk/_writer.py
mmv_hitl4trk/add_models.py
mmv_hitl4trk/custom_models.json
mmv_hitl4trk/napari.yaml
mmv_hitl4trk/_tests/__init__.py
mmv_hitl4trk/_tests/test_evaluation.py
mmv_hitl4trk/_tests/test_widget.py
mmv_hitl4trk/_tests/data/images/Raw Image.tif
mmv_hitl4trk/_tests/data/segmentation/GT.tif
mmv_hitl4trk/_tests/data/segmentation/GT_false_negative_2.tif
mmv_hitl4trk/_tests/data/segmentation/centroid_ausserhalb.tif
mmv_hitl4trk/_tests/data/segmentation/false positive.tif
mmv_hitl4trk/_tests/data/segmentation/false positive_1.tif
mmv_hitl4trk/_tests/data/segmentation/false_negative.tif
mmv_hitl4trk/_tests/data/segmentation/false_negative_1.tif
mmv_hitl4trk/_tests/data/segmentation/false_negative_2.tif
mmv_hitl4trk/_tests/data/segmentation/falsely_cut.tif
mmv_hitl4trk/_tests/data/segmentation/falsely_merged.tif
mmv_hitl4trk/_tests/data/segmentation/zelle_kleiner.tif
mmv_hitl4trk/_tests/data/tracks/GT_tracks.npy
mmv_hitl4trk/_tests/data/tracks/ID_twice.npy
mmv_hitl4trk/_tests/data/tracks/added_edge.npy
mmv_hitl4trk/_tests/data/tracks/centroid_outside.npy
mmv_hitl4trk/_tests/data/tracks/deleted_edge.npy
mmv_hitl4trk/_tests/data/tracks/falsely_cut_tracks.npy
mmv_hitl4trk/_tests/data/tracks/offset.npy
mmv_hitl4trk/_tests/data/tracks/switch.npy
mmv_hitl4trk/models/Neutrophil granulocytes
mmv_hitl4trk/ressources/celltracking_logo.jpg
mmv_hitl4trk-1.0.0.dist-info/LICENSE
mmv_hitl4trk-1.0.0.dist-info/METADATA
mmv_hitl4trk-1.0.0.dist-info/WHEEL
mmv_hitl4trk-1.0.0.dist-info/entry_points.txt
mmv_hitl4trk-1.0.0.dist-info/top_level.txt
mmv_hitl4trk-1.0.0.dist-info/RECORD
