Metadata-Version: 2.1
Name: mmv_hitl4trk
Version: 1.0.0
Summary: A simple plugin to use with napari
Home-page: https://github.com/MMV-Lab/mmv_hitl4trk
Author: lennart kowitz
Author-email: lennart.kowitz@isas.de
License: BSD-3-Clause
Project-URL: Bug Tracker, https://github.com/MMV-Lab/mmv_hitl4trk/issues
Project-URL: Documentation, https://github.com/MMV-Lab/mmv_hitl4trk#README.md
Project-URL: Source Code, https://github.com/MMV-Lab/mmv_hitl4trk
Project-URL: User Support, https://github.com/MMV-Lab/mmv_hitl4trk/issues
Classifier: Development Status :: 3 - Alpha
Classifier: Intended Audience :: Science/Research
Classifier: Framework :: napari
Classifier: Topic :: Scientific/Engineering :: Image Processing
Classifier: Programming Language :: Python
Classifier: Programming Language :: Python :: 3
Classifier: Programming Language :: Python :: 3.7
Classifier: Programming Language :: Python :: 3.8
Classifier: Programming Language :: Python :: 3.9
Classifier: Programming Language :: Python :: 3.10
Classifier: Operating System :: OS Independent
Classifier: License :: OSI Approved :: BSD License
Requires-Python: >=3.7
License-File: LICENSE
Requires-Dist: numpy
Requires-Dist: npe2
Requires-Dist: napari-plugin-engine >=0.1.4
Requires-Dist: napari
Requires-Dist: zarr
Requires-Dist: cellpose ==2.1.0
Requires-Dist: keyboard
Requires-Dist: matplotlib
Requires-Dist: aicsimageio
Requires-Dist: scipy >=1.11.0
